computils/__init__.py
computils/factory.py
computils/fast_eval.py
computils/finite_difference.py
computils/gaussian_elim_spp.py
computils/globals.py
computils/interpolation.py
computils/matrix_computations.py
computils/parallelization.py
computils/parameter_transformations.py
computils/performance_checking.py
computils/sorting_algorithms.py
computils/type_utils.py
tests/matrix_computations_tests.py
tests/numerical_derivatives_tests.py
tests/parameter_transformation_tests.py
tests/test_utils.py
computils-0.0.2.dist-info/LICENSE
computils-0.0.2.dist-info/METADATA
computils-0.0.2.dist-info/WHEEL
computils-0.0.2.dist-info/top_level.txt
computils-0.0.2.dist-info/RECORD
