Metadata-Version: 2.1
Name: computils
Version: 0.0.2
Summary: A package collecting functionality for various numerical computations (numerical differentiation, interpolation, optimization, sorting, parallelization).
Author-email: Karim Moussa <research@k-moussa.com>
Project-URL: Homepage, https://github.com/k-moussa/computils
Classifier: Programming Language :: Python :: 3
Classifier: License :: OSI Approved :: MIT License
Classifier: Operating System :: OS Independent
Requires-Python: >=3.7
License-File: LICENSE
